{"53":{"unit-id":"usopp_ts_evolved","type":"upgrade_unit","time":51,"position":{"y":122.361,"x":319.294,"z":128.733},"wave":14},"43":{"unit-id":"cell_super_perfect","type":"upgrade_unit","time":56,"position":{"y":125.697,"x":319.877,"z":117.261},"wave":11},"51":{"unit-id":"tengen_2_evolved","type":"upgrade_unit","time":55,"position":{"y":122.361,"x":316.9,"z":119.162},"wave":14},"41":{"unit-id":"cell_super_perfect","type":"upgrade_unit","time":53,"position":{"y":125.697,"x":319.877,"z":117.261},"wave":10},"47":{"unit-id":"tengen_2_evolved","type":"upgrade_unit","time":45,"position":{"y":122.361,"x":317.439,"z":114.648},"wave":13},"37":{"unit-id":"tengen_2_evolved","type":"upgrade_unit","time":56,"position":{"y":122.361,"x":316.9,"z":119.162},"wave":9},"45":{"unit-id":"cell_super_perfect","type":"upgrade_unit","time":59,"position":{"y":125.697,"x":319.877,"z":117.261},"wave":12},"35":{"unit-id":"tengen_2_evolved","type":"upgrade_unit","time":58,"position":{"y":122.361,"x":317.386,"z":116.873},"wave":9},"59":{"unit-id":"usopp_ts_evolved","type":"upgrade_unit","time":58,"position":{"y":122.361,"x":323.196,"z":134.438},"wave":15},"49":{"unit-id":"tengen_2_evolved","type":"upgrade_unit","time":59,"position":{"y":122.361,"x":317.386,"z":116.873},"wave":14},"39":{"unit-id":"cell_super_perfect","type":"upgrade_unit","time":53,"position":{"y":125.697,"x":319.877,"z":117.261},"wave":9},"29":{"unit-id":"speedwagon","type":"upgrade_unit","time":55,"position":{"y":122.361,"x":304.655,"z":128.369},"wave":7},"61":{"unit-id":"usopp_ts_evolved","type":"upgrade_unit","time":57,"position":{"y":122.361,"x":323.196,"z":134.438},"wave":15},"1":{"unit-id":"speedwagon","type":"spawn_unit","time":55,"position":{"y":122.061,"x":304.655,"z":128.369},"wave":1},"60":{"unit-id":"usopp_ts_evolved","type":"upgrade_unit","time":58,"position":{"y":122.361,"x":323.196,"z":134.438},"wave":15},"3":{"unit-id":"cell_super_perfect","type":"spawn_unit","time":56,"position":{"y":125.397,"x":319.877,"z":117.261},"wave":2},"2":{"unit-id":"tengen_2_evolved","type":"spawn_unit","time":58,"position":{"y":122.061,"x":317.386,"z":116.873},"wave":2},"5":{"unit-id":"speedwagon","type":"spawn_unit","time":53,"position":{"y":122.061,"x":312.05,"z":128.385},"wave":2},"4":{"unit-id":"speedwagon","type":"spawn_unit","time":54,"position":{"y":122.061,"x":308.265,"z":128.03},"wave":2},"7":{"unit-id":"speedwagon","type":"upgrade_unit","time":55,"position":{"y":122.361,"x":308.265,"z":128.03},"wave":3},"6":{"unit-id":"speedwagon","type":"upgrade_unit","time":57,"position":{"y":122.361,"x":312.05,"z":128.385},"wave":3},"9":{"unit-id":"usopp_ts_evolved","type":"spawn_unit","time":47,"position":{"y":122.061,"x":319.294,"z":128.733},"wave":3},"8":{"unit-id":"speedwagon","type":"upgrade_unit","time":54,"position":{"y":122.361,"x":304.655,"z":128.369},"wave":3},"27":{"unit-id":"speedwagon","type":"upgrade_unit","time":59,"position":{"y":122.361,"x":312.05,"z":128.385},"wave":7},"17":{"unit-id":"speedwagon","type":"upgrade_unit","time":56,"position":{"y":122.361,"x":312.05,"z":128.385},"wave":5},"13":{"unit-id":"speedwagon","type":"upgrade_unit","time":55,"position":{"y":122.361,"x":312.05,"z":128.385},"wave":4},"21":{"unit-id":"tengen_2_evolved","type":"spawn_unit","time":53,"position":{"y":122.061,"x":317.439,"z":114.648},"wave":6},"11":{"unit-id":"speedwagon","type":"upgrade_unit","time":58,"position":{"y":122.361,"x":304.655,"z":128.369},"wave":4},"23":{"unit-id":"erwin","type":"spawn_unit","time":46,"position":{"y":125.397,"x":321.106,"z":120.39},"wave":6},"42":{"unit-id":"cell_super_perfect","type":"upgrade_unit","time":51,"position":{"y":125.697,"x":319.877,"z":117.261},"wave":10},"52":{"unit-id":"tengen_2_evolved","type":"upgrade_unit","time":54,"position":{"y":122.361,"x":316.9,"z":119.162},"wave":14},"40":{"unit-id":"cell_super_perfect","type":"upgrade_unit","time":55,"position":{"y":125.697,"x":319.877,"z":117.261},"wave":10},"50":{"unit-id":"tengen_2_evolved","type":"upgrade_unit","time":58,"position":{"y":122.361,"x":317.386,"z":116.873},"wave":14},"36":{"unit-id":"tengen_2_evolved","type":"upgrade_unit","time":57,"position":{"y":122.361,"x":316.9,"z":119.162},"wave":9},"46":{"unit-id":"cell_super_perfect","type":"upgrade_unit","time":57,"position":{"y":125.697,"x":319.877,"z":117.261},"wave":13},"34":{"unit-id":"tengen_2_evolved","type":"upgrade_unit","time":59,"position":{"y":122.361,"x":317.386,"z":116.873},"wave":9},"44":{"unit-id":"cell_super_perfect","type":"upgrade_unit","time":55,"position":{"y":125.697,"x":319.877,"z":117.261},"wave":11},"48":{"unit-id":"tengen_2_evolved","type":"upgrade_unit","time":43,"position":{"y":122.361,"x":317.439,"z":114.648},"wave":13},"58":{"unit-id":"usopp_ts_evolved","type":"upgrade_unit","time":0,"position":{"y":122.361,"x":321.48,"z":131.804},"wave":14},"28":{"unit-id":"speedwagon","type":"upgrade_unit","time":57,"position":{"y":122.361,"x":308.265,"z":128.03},"wave":7},"38":{"unit-id":"cell_super_perfect","type":"upgrade_unit","time":54,"position":{"y":125.697,"x":319.877,"z":117.261},"wave":9},"57":{"unit-id":"usopp_ts_evolved","type":"upgrade_unit","time":1,"position":{"y":122.361,"x":321.48,"z":131.804},"wave":14},"56":{"unit-id":"usopp_ts_evolved","type":"upgrade_unit","time":1,"position":{"y":122.361,"x":321.48,"z":131.804},"wave":14},"55":{"unit-id":"usopp_ts_evolved","type":"upgrade_unit","time":3,"position":{"y":122.361,"x":319.294,"z":128.733},"wave":14},"54":{"unit-id":"usopp_ts_evolved","type":"upgrade_unit","time":50,"position":{"y":122.361,"x":319.294,"z":128.733},"wave":14},"33":{"unit-id":"tengen_2_evolved","type":"upgrade_unit","time":54,"position":{"y":122.361,"x":317.439,"z":114.648},"wave":8},"32":{"unit-id":"tengen_2_evolved","type":"upgrade_unit","time":55,"position":{"y":122.361,"x":317.439,"z":114.648},"wave":8},"31":{"unit-id":"hoshino_evolved","type":"upgrade_unit","time":58,"position":{"y":123.212,"x":300.759,"z":120.803},"wave":8},"30":{"unit-id":"hoshino_evolved","type":"upgrade_unit","time":59,"position":{"y":123.212,"x":300.759,"z":120.803},"wave":8},"15":{"unit-id":"speedwagon","type":"upgrade_unit","time":59,"position":{"y":122.361,"x":304.655,"z":128.369},"wave":5},"18":{"unit-id":"hoshino_evolved","type":"upgrade_unit","time":59,"position":{"y":123.212,"x":300.759,"z":120.803},"wave":6},"19":{"unit-id":"cell_super_perfect","type":"upgrade_unit","time":57,"position":{"y":125.697,"x":319.877,"z":117.261},"wave":6},"25":{"unit-id":"erwin","type":"spawn_unit","time":44,"position":{"y":125.397,"x":318.713,"z":120.198},"wave":6},"14":{"unit-id":"hoshino_evolved","type":"spawn_unit","time":47,"position":{"y":122.061,"x":300.759,"z":120.803},"wave":4},"24":{"unit-id":"erwin","type":"spawn_unit","time":45,"position":{"y":125.397,"x":321.101,"z":122.406},"wave":6},"16":{"unit-id":"speedwagon","type":"upgrade_unit","time":58,"position":{"y":122.361,"x":308.265,"z":128.03},"wave":5},"26":{"unit-id":"erwin","type":"spawn_unit","time":43,"position":{"y":125.397,"x":318.939,"z":122.497},"wave":6},"20":{"unit-id":"usopp_ts_evolved","type":"spawn_unit","time":55,"position":{"y":122.061,"x":323.196,"z":134.438},"wave":6},"12":{"unit-id":"speedwagon","type":"upgrade_unit","time":57,"position":{"y":122.361,"x":308.265,"z":128.03},"wave":4},"22":{"unit-id":"tengen_2_evolved","type":"spawn_unit","time":50,"position":{"y":122.061,"x":316.9,"z":119.162},"wave":6},"10":{"unit-id":"usopp_ts_evolved","type":"spawn_unit","time":45,"position":{"y":122.061,"x":321.48,"z":131.804},"wave":3}}